paystackpyAPI/__init__.py
paystackpyAPI/paystack.py
paystackpyAPI/transaction.py
paystackpyAPI-2.0.0.dist-info/LICENSE
paystackpyAPI-2.0.0.dist-info/METADATA
paystackpyAPI-2.0.0.dist-info/WHEEL
paystackpyAPI-2.0.0.dist-info/entry_points.txt
paystackpyAPI-2.0.0.dist-info/top_level.txt
paystackpyAPI-2.0.0.dist-info/RECORD
